{
  "types": [
    {
      "name": "AnalyzedClass",
      "namespace": "scala.tools.sci.api",
      "target": "Java",
      "type": "record",
      "fields": [
        { "name": "compilationTimestamp", "type": "long"   },
        { "name": "name",        "type": "String"          },
        { "name": "api",         "type": "lazy Companions" },
        { "name": "apiHash",     "type": "int"             },
        { "name": "nameHashes",  "type": "NameHash*"       },
        { "name": "hasMacro",    "type": "boolean"         },
        {
          "name": "extraHash",
          "type": "int",
          "since": "1.2.0",
          "default": "apiHash"
        }
      ]
    },
    {
      "name": "Companions",
      "namespace": "scala.tools.sci.api",
      "target": "Java",
      "type": "record",
      "fields": [
        { "name": "classApi",  "type": "ClassLike" },
        { "name": "objectApi", "type": "ClassLike" }
      ]
    },
    {
      "name": "NameHash",
      "namespace": "scala.tools.sci.api",
      "target": "Java",
      "type": "record",
      "fields": [
        { "name": "name", "type": "String" },
        { "name": "scope", "type": "scala.tools.sci.UseScope" },
        { "name": "hash", "type": "int"    }
      ]
    },
    {
      "name": "Package",
      "namespace": "scala.tools.sci.api",
      "target": "Java",
      "type": "record",
      "fields": [
        { "name": "name", "type": "String" }
      ]
    },
    {
      "name": "Access",
      "namespace": "scala.tools.sci.api",
      "target": "Java",
      "type": "interface",

      "types": [
        {
          "name": "Public",
          "namespace": "scala.tools.sci.api",
          "target": "Java",
          "type": "record"
        },
        {
          "name": "Qualified",
          "namespace": "scala.tools.sci.api",
          "target": "Java",
          "type": "interface",
          "fields": [
            { "name": "qualifier", "type": "Qualifier" }
          ],

          "types": [
            { "name": "Protected", "namespace": "scala.tools.sci.api", "target": "Java", "type": "record" },
            { "name": "Private",   "namespace": "scala.tools.sci.api", "target": "Java", "type": "record" }
          ]
        }
      ]
    },
    {
      "name": "Qualifier",
      "namespace": "scala.tools.sci.api",
      "target": "Java",
      "type": "interface",
      "types": [
        { "name": "Unqualified",   "namespace": "scala.tools.sci.api", "target": "Java", "type": "record" },
        { "name": "ThisQualifier", "namespace": "scala.tools.sci.api", "target": "Java", "type": "record" },
        {
          "name": "IdQualifier",
          "namespace": "scala.tools.sci.api",
          "target": "Java",
          "type": "record",
          "fields": [
            { "name": "value", "type": "String" }
          ]
        }
      ]
    },
    {
      "name": "ParameterList",
      "namespace": "scala.tools.sci.api",
      "target": "Java",
      "type": "record",
      "fields": [
        { "name": "parameters", "type": "MethodParameter*" },
        { "name": "isImplicit", "type": "boolean"          }
      ]
    },
    {
      "name": "MethodParameter",
      "namespace": "scala.tools.sci.api",
      "target": "Java",
      "type": "record",
      "fields": [
        { "name": "name",       "type": "String"            },
        { "name": "tpe",        "type": "Type"              },
        { "name": "hasDefault", "type": "boolean"           },
        { "name": "modifier",   "type": "ParameterModifier" }
      ]
    },
    {
      "name": "TypeParameter",
      "namespace": "scala.tools.sci.api",
      "target": "Java",
      "type": "record",
      "fields": [
        { "name": "id",             "type": "String"         },
        { "name": "annotations",    "type": "Annotation*"    },
        { "name": "typeParameters", "type": "TypeParameter*" },
        { "name": "variance",       "type": "Variance"       },
        { "name": "lowerBound",     "type": "Type"           },
        { "name": "upperBound",     "type": "Type"           }
      ]
    },
    {
      "name": "Annotation",
      "namespace": "scala.tools.sci.api",
      "target": "Java",
      "type": "record",
      "fields": [
        { "name": "base",      "type": "Type"                },
        { "name": "arguments", "type": "AnnotationArgument*" }
      ]
    },
    {
      "name": "AnnotationArgument",
      "namespace": "scala.tools.sci.api",
      "target": "Java",
      "type": "record",
      "fields": [
        { "name": "name",  "type": "String" },
        { "name": "value", "type": "String" }
      ]
    },
    {
      "name": "Variance",
      "namespace": "scala.tools.sci.api",
      "target": "Java",
      "type": "enum",
      "symbols": [ "Contravariant", "Covariant", "Invariant" ]
    },
    {
      "name": "ParameterModifier",
      "namespace": "scala.tools.sci.api",
      "target": "Java",
      "type": "enum",
      "symbols": [ "Repeated", "Plain", "ByName" ]
    },
    {
      "name": "DefinitionType",
      "namespace": "scala.tools.sci.api",
      "target": "Java",
      "type": "enum",
      "symbols": [ "Trait", "ClassDef", "Module", "PackageModule" ]
    },
    {
      "name": "Path",
      "namespace": "scala.tools.sci.api",
      "target": "Java",
      "type": "record",
      "fields": [
        { "name": "components", "type": "PathComponent*" }
      ]
    },
    {
      "name": "PathComponent",
      "namespace": "scala.tools.sci.api",
      "target": "Java",
      "type": "interface",
      "types": [
        {
          "name": "Super",
          "namespace": "scala.tools.sci.api",
          "target": "Java",
          "type": "record",
          "fields": [
            { "name": "qualifier", "type": "Path" }
          ]
        },
        { "name": "This", "namespace": "scala.tools.sci.api", "target": "Java", "type": "record" },
        {
          "name": "Id",
          "namespace": "scala.tools.sci.api",
          "target": "Java",
          "type": "record",
          "fields": [
            { "name": "id", "type": "String" }
          ]
        }
      ]
    },
    {
      "name": "DependencyContext",
      "doc": [
        "Enumeration of existing dependency contexts.",
        "Dependency contexts represent the various kind of dependencies that",
        "can exist between symbols."
      ],
      "namespace": "scala.tools.sci.api",
      "target": "Java",
      "type": "enum",
      "symbols": [
        {
          "name": "DependencyByMemberRef",
          "doc": [
            "Represents a direct dependency between two symbols :",
            "object Foo",
            "object Bar { def foo = Foo }"
          ]
        },
        {
          "name": "DependencyByInheritance",
          "doc": [
            "Represents an inheritance dependency between two symbols :",
            "class A",
            "class B extends A"
          ]
        },
        {
          "name": "LocalDependencyByInheritance",
          "doc": [
            "Represents an inheritance dependency between a local class",
            "and a non local class:",
            "  // A.scala",
            "  class A",
            "  // B.scala",
            "  class B {",
            "    def foo = {",
            "      class Local extends A",
            "    }",
            "  }"
          ]
        }
      ]
    },
    {
      "name": "InternalDependency",
      "namespace": "scala.tools.sci.api",
      "target": "Java",
      "type": "record",
      "fields": [
        { "name": "sourceClassName", "type": "String"                      },
        { "name": "targetClassName", "type": "String"                      },
        { "name": "context",         "type": "scala.tools.sci.api.DependencyContext" }
      ]
    },
    {
      "name": "ExternalDependency",
      "namespace": "scala.tools.sci.api",
      "target": "Java",
      "type": "record",
      "fields": [
        { "name": "sourceClassName",        "type": "String"                      },
        { "name": "targetProductClassName", "type": "String"                      },
        { "name": "targetClass",            "type": "scala.tools.sci.api.AnalyzedClass"     },
        { "name": "context",                "type": "scala.tools.sci.api.DependencyContext" }
      ]
    }
  ]
}
